django_dynamic_form_fields-0.2.0.dist-info/METADATA
django_dynamic_form_fields-0.2.0.dist-info/RECORD
django_dynamic_form_fields-0.2.0.dist-info/WHEEL
django_dynamic_form_fields-0.2.0.dist-info/top_level.txt
dynamic_fields/__init__.py
dynamic_fields/apps.py
dynamic_fields/fields.py
dynamic_fields/urls.py
dynamic_fields/views.py
dynamic_fields/static/dynamic_fields/js/dynamic_fields.js
dynamic_fields/templates/dynamic_fields/forms/widgets/dynamic_select.html
