Metadata-Version: 2.1
Name: django-dynamic-form-fields
Version: 0.2.0
Summary: Dynamically update choice fields based on dependent fields in django
Home-page: https://gitlab.com/dannosaur/django-dynamic-form-fields
Author: dannosaur
Author-email: me@dannosaur.com
License: UNKNOWN
Platform: UNKNOWN
Requires-Python: >=3.5
Requires-Dist: django (<2.1,>=1.11)
